zappa_file_widget/__init__.py
zappa_file_widget/file_widget.py
zappa_file_widget/url_widget.py
zappa_file_widget-0.1.5.dist-info/DESCRIPTION.rst
zappa_file_widget-0.1.5.dist-info/METADATA
zappa_file_widget-0.1.5.dist-info/RECORD
zappa_file_widget-0.1.5.dist-info/WHEEL
zappa_file_widget-0.1.5.dist-info/metadata.json
zappa_file_widget-0.1.5.dist-info/top_level.txt
